odoo/addons/stock_available_location_get_domain/README.rst
odoo/addons/stock_available_location_get_domain/__init__.py
odoo/addons/stock_available_location_get_domain/__manifest__.py
odoo/addons/stock_available_location_get_domain/i18n/it.po
odoo/addons/stock_available_location_get_domain/i18n/stock_available_location_get_domain.pot
odoo/addons/stock_available_location_get_domain/models/__init__.py
odoo/addons/stock_available_location_get_domain/models/product_product.py
odoo/addons/stock_available_location_get_domain/readme/CONTRIBUTORS.md
odoo/addons/stock_available_location_get_domain/readme/DESCRIPTION.md
odoo/addons/stock_available_location_get_domain/readme/USAGE.md
odoo/addons/stock_available_location_get_domain/static/description/icon.png
odoo/addons/stock_available_location_get_domain/static/description/index.html
odoo/addons/stock_available_location_get_domain/tests/__init__.py
odoo/addons/stock_available_location_get_domain/tests/test_location_domain.py
odoo_addon_stock_available_location_get_domain-18.0.1.0.0.2.dist-info/METADATA
odoo_addon_stock_available_location_get_domain-18.0.1.0.0.2.dist-info/WHEEL
odoo_addon_stock_available_location_get_domain-18.0.1.0.0.2.dist-info/top_level.txt
odoo_addon_stock_available_location_get_domain-18.0.1.0.0.2.dist-info/RECORD
