Metadata-Version: 2.1
Name: odoo-addon-stock_available_location_get_domain
Version: 18.0.1.0.0.2
Requires-Python: >=3.10
Requires-Dist: odoo==18.0.*
Summary: This is a technical helper module in order to reuse the standard _get_domain_locations() function for locations and not quants
Home-page: https://github.com/OCA/stock-logistics-availability
License: AGPL-3
Author: ACSONE SA/NV,Odoo Community Association (OCA)
Author-email: support@odoo-community.org
Classifier: Programming Language :: Python
Classifier: Framework :: Odoo
Classifier: Framework :: Odoo :: 18.0
Classifier: License :: OSI Approved :: GNU Affero General Public License v3
